flm/__init__.py
flm/__main__.py
flm/_autounichars.py
flm/counter.py
flm/docgen/__init__.py
flm/docgen/__main__.py
flm/docgen/docgen.py
flm/feature/__init__.py
flm/feature/_base.py
flm/feature/annotations.py
flm/feature/baseformatting.py
flm/feature/cells.py
flm/feature/cite.py
flm/feature/defterm.py
flm/feature/endnotes.py
flm/feature/enumeration.py
flm/feature/floats.py
flm/feature/graphics.py
flm/feature/headings.py
flm/feature/href.py
flm/feature/math.py
flm/feature/numbering.py
flm/feature/refs.py
flm/feature/substmacros.py
flm/feature/theorems.py
flm/feature/verbatim.py
flm/flmdocument.py
flm/flmdump.py
flm/flmenvironment.py
flm/flmfragment.py
flm/flmrecomposer/__init__.py
flm/flmrecomposer/_recomposer.py
flm/flmrecomposer/purelatex.py
flm/flmrendercontext.py
flm/flmspecinfo.py
flm/fragmentrenderer/__init__.py
flm/fragmentrenderer/_base.py
flm/fragmentrenderer/html.py
flm/fragmentrenderer/latex.py
flm/fragmentrenderer/markdown.py
flm/fragmentrenderer/text.py
flm/main/__init__.py
flm/main/_find_exe.py
flm/main/_inspectimagefile.py
flm/main/_util.py
flm/main/configmerger.py
flm/main/default_config.yaml
flm/main/feature_graphics_collection.py
flm/main/importclass.py
flm/main/main.py
flm/main/oshelper.py
flm/main/run.py
flm/main/template.py
flm/main/templates/html/docgen.yaml
flm/main/templates/html/none.yaml
flm/main/templates/html/simple.html
flm/main/templates/html/simple.yaml
flm/main/templates/latex/docgen.yaml
flm/main/templates/latex/none.yaml
flm/main/templates/latex/revtex.tex
flm/main/templates/latex/revtex.yaml
flm/main/templates/latex/simple.tex
flm/main/templates/latex/simple.yaml
flm/main/templates/markdown/simple.md
flm/main/templates/markdown/simple.yaml
flm/main/templates/text/docgen.yaml
flm/main/templates/text/simple.txt
flm/main/templates/text/simple.yaml
flm/main/watch.py
flm/main/workflow/__init__.py
flm/main/workflow/_base.py
flm/main/workflow/flmlatex.py
flm/main/workflow/runlatexpdf.py
flm/main/workflow/templatebasedworkflow.py
flm_core-0.3.0a23.dist-info/LICENSE
flm_core-0.3.0a23.dist-info/METADATA
flm_core-0.3.0a23.dist-info/WHEEL
flm_core-0.3.0a23.dist-info/entry_points.txt
flm_core-0.3.0a23.dist-info/RECORD
