Metadata-Version: 2.3
Name: flm-core
Version: 0.3.0a23
Summary: Flexible Latex-like Markup
License: MIT
Author: Philippe Faist
Requires-Python: >=3.9,<4.0
Classifier: License :: OSI Approved :: MIT License
Classifier: Programming Language :: Python :: 3
Classifier: Programming Language :: Python :: 3.9
Classifier: Programming Language :: Python :: 3.10
Classifier: Programming Language :: Python :: 3.11
Classifier: Programming Language :: Python :: 3.12
Classifier: Programming Language :: Python :: 3.13
Provides-Extra: maincmdl
Requires-Dist: PyYAML (>=5.0) ; extra == "maincmdl"
Requires-Dist: cairosvg (>=2.7.1,<3.0.0) ; extra == "maincmdl"
Requires-Dist: colorlog (>=6.7.0,<7.0.0) ; extra == "maincmdl"
Requires-Dist: pillow (>=10.4.0,<11.0.0) ; extra == "maincmdl"
Requires-Dist: pylatexenc (>=3.0a32,<4.0)
Requires-Dist: pypdf (>=4.3.1,<5.0.0) ; extra == "maincmdl"
Requires-Dist: python-frontmatter (>=1.0.0,<2.0.0) ; extra == "maincmdl"
Requires-Dist: watchfiles (>=1.0.4,<2.0.0) ; extra == "maincmdl"
Requires-Dist: websockets (>=15.0,<16.0) ; extra == "maincmdl"
